copycode/__init__.py
copycode/main.py
copycode-0.2.3.dist-info/LICENSE
copycode-0.2.3.dist-info/METADATA
copycode-0.2.3.dist-info/WHEEL
copycode-0.2.3.dist-info/entry_points.txt
copycode-0.2.3.dist-info/top_level.txt
copycode-0.2.3.dist-info/RECORD
