Metadata-Version: 2.2
Name: copycode
Version: 0.2.3
Summary: Copy all your code to your clipboard or a file with one command.
Home-page: https://github.com/MartinVeltman/CopyCode
Author: MartinVeltman
Author-email: martin.veltman@winvent.nl
License: MIT
Project-URL: Source Code, https://github.com/MartinVeltman/CopyCode
Classifier: Programming Language :: Python :: 3
Classifier: License :: OSI Approved :: MIT License
Requires-Python: >=3.6
License-File: LICENSE
Requires-Dist: pyperclip
Requires-Dist: pyyaml
Dynamic: author
Dynamic: author-email
Dynamic: classifier
Dynamic: description
Dynamic: description-content-type
Dynamic: home-page
Dynamic: license
Dynamic: project-url
Dynamic: requires-dist
Dynamic: requires-python
Dynamic: summary
